{"resource":"commonplayerinfo","parameters":[{"PlayerID":200826},{"LeagueID":null}],"resultSets":[{"name":"CommonPlayerInfo","headers":["PERSON_ID","FIRST_NAME","LAST_NAME","DISPLAY_FIRST_LAST","DISPLAY_LAST_COMMA_FIRST","DISPLAY_FI_LAST","BIRTHDATE","SCHOOL","COUNTRY","LAST_AFFILIATION","HEIGHT","WEIGHT","SEASON_EXP","JERSEY","POSITION","ROSTERSTATUS","TEAM_ID","TEAM_NAME","TEAM_ABBREVIATION","TEAM_CODE","TEAM_CITY","PLAYERCODE","FROM_YEAR","TO_YEAR","DLEAGUE_FLAG","NBA_FLAG","GAMES_PLAYED_FLAG","DRAFT_YEAR","DRAFT_ROUND","DRAFT_NUMBER"],"rowSet":[[200826,"J.J.","Barea","J.J. Barea","Barea, J.J.","J. Barea","1984-06-26T00:00:00","Northeastern","Puerto Rico","Northeastern/Puerto Rico","6-0","185",13,"5","Guard","Active",1610612742,"Mavericks","DAL","mavericks","Dallas","j.j._barea",2006,2019,"Y","Y","Y","Undrafted","Undrafted","Undrafted"]]},{"name":"PlayerHeadlineStats","headers":["PLAYER_ID","PLAYER_NAME","TimeFrame","PTS","AST","REB","PIE"],"rowSet":[[200826,"J.J. Barea","2018-19",10.900000,5.600000,2.500000,0.131]]},{"name":"AvailableSeasons","headers":["SEASON_ID"],"rowSet":[["12006"],["22006"],["42006"],["12007"],["22007"],["42007"],["12008"],["22008"],["42008"],["12009"],["22009"],["42009"],["12010"],["22010"],["42010"],["12011"],["22011"],["12012"],["22012"],["12013"],["22013"],["12014"],["22014"],["42014"],["12015"],["22015"],["42015"],["12016"],["22016"],["12017"],["22017"],["12018"],["22018"]]}]}