{"resource":"commonplayerinfo","parameters":[{"PlayerID":2294},{"LeagueID":null}],"resultSets":[{"name":"CommonPlayerInfo","headers":["PERSON_ID","FIRST_NAME","LAST_NAME","DISPLAY_FIRST_LAST","DISPLAY_LAST_COMMA_FIRST","DISPLAY_FI_LAST","BIRTHDATE","SCHOOL","COUNTRY","LAST_AFFILIATION","HEIGHT","WEIGHT","SEASON_EXP","JERSEY","POSITION","ROSTERSTATUS","TEAM_ID","TEAM_NAME","TEAM_ABBREVIATION","TEAM_CODE","TEAM_CITY","PLAYERCODE","FROM_YEAR","TO_YEAR","DLEAGUE_FLAG","NBA_FLAG","GAMES_PLAYED_FLAG","DRAFT_YEAR","DRAFT_ROUND","DRAFT_NUMBER"],"rowSet":[[2294,"Charlie","Bell","Charlie Bell","Bell, Charlie","C. Bell","1979-03-12T00:00:00","Michigan State"," ","Michigan State/USA","6-3","200",7,"34","Guard","Active",1610612749,"Bucks","MIL","bucks","Milwaukee","charlie_bell",2001,2010,"N","Y","Y","Undrafted","Undrafted","Undrafted"]]},{"name":"PlayerHeadlineStats","headers":["PLAYER_ID","PLAYER_NAME","TimeFrame","PTS","AST","REB","ALL_STAR_APPEARANCES"],"rowSet":[[2294,"Charlie Bell","career",8.500,2.300,2.200,0]]},{"name":"AvailableSeasons","headers":["SEASON_ID"],"rowSet":[["12001"],["22001"],["12005"],["22005"],["42005"],["12006"],["22006"],["12007"],["22007"],["12008"],["22008"],["12009"],["22009"],["42009"],["12010"],["22010"]]}]}