{"resource":"commonplayerinfo","parameters":[{"PlayerID":76257},{"LeagueID":null}],"resultSets":[{"name":"CommonPlayerInfo","headers":["PERSON_ID","FIRST_NAME","LAST_NAME","DISPLAY_FIRST_LAST","DISPLAY_LAST_COMMA_FIRST","DISPLAY_FI_LAST","BIRTHDATE","SCHOOL","COUNTRY","LAST_AFFILIATION","HEIGHT","WEIGHT","SEASON_EXP","JERSEY","POSITION","ROSTERSTATUS","TEAM_ID","TEAM_NAME","TEAM_ABBREVIATION","TEAM_CODE","TEAM_CITY","PLAYERCODE","FROM_YEAR","TO_YEAR","DLEAGUE_FLAG","NBA_FLAG","GAMES_PLAYED_FLAG","DRAFT_YEAR","DRAFT_ROUND","DRAFT_NUMBER"],"rowSet":[[76257,"Allan","Bristow","Allan Bristow","Bristow, Allan","A. Bristow","1951-08-23T00:00:00","Virginia Tech","USA","Toledo; Virginia Tech/USA","6-7","210",8,"23","Forward","Active",1610612759,"Spurs","SAS","spurs","San Antonio","HISTADD_allan_bristow",1973,1982,"N","Y","Y","1973","2","21"]]},{"name":"PlayerHeadlineStats","headers":["PLAYER_ID","PLAYER_NAME","TimeFrame","PTS","AST","REB","ALL_STAR_APPEARANCES"],"rowSet":[[76257,"Allan Bristow","career",7.900,3.200,4.000,0]]},{"name":"AvailableSeasons","headers":["SEASON_ID"],"rowSet":[["21973"],["21974"],["21976"],["41976"],["21977"],["41977"],["21978"],["41978"],["21979"],["21980"],["21981"],["21982"]]}]}